[

{"quote":"Perfection is attained by slow degrees, it requires the hand of time.", "author":"Voltaire"},
{"quote":"Don't cry because it's over, smile because it happened.", "author":"Dr. Seuss" },
{"quote":"Be yourself, everyone else is already taken.", "author":"Oscar Wilde" },
{"quote":"Two things are infinite: the universe and human stupidity, and I'm not sure about the universe.", "author":"Albert Einstein" },
{"quote":"You only live once, but if you do it right, once is enough.", "author":"Mae West" },
{"quote":"Be the change that you wish to see in the world.", "author":"Mahatma Gandhi" },
{"quote":"If you want to know what a man's like, take a good look at how he treats his inferiors, not his equals.", "author":"J.K.Rowling" },
{"quote":"No one can make you feel inferior without your consent.", "author":"Eleanor Roosevelt" },
{"quote":"Always forgive your enemies, nothing annoys them so much.", "author":"Oscar Wilde" }
]
